[
  {
    "id": "exp_20260417751045240733316",
    "date": "2026-04-02",
    "description": "Rd",
    "amount": 2000,
    "createdAt": "2026-04-02T04:35:24.073Z",
    "updatedAt": "2026-04-02T04:35:24.073Z",
    "category": "Investment"
  },
  {
    "id": "exp_20260417750685295746801",
    "date": "2026-04-01",
    "description": "Parlour",
    "amount": 300,
    "createdAt": "2026-04-01T18:35:29.574Z",
    "updatedAt": "2026-04-01T18:35:29.575Z",
    "category": "Personal Care"
  },
  {
    "id": "exp_20260417750685617927733",
    "date": "2026-04-01",
    "description": "PMT",
    "amount": 20,
    "createdAt": "2026-04-01T18:36:01.792Z",
    "updatedAt": "2026-04-01T18:36:01.792Z",
    "category": "Transportation"
  },
  {
    "id": "exp_20260417750686547541237",
    "date": "2026-04-01",
    "description": "Canteen",
    "amount": 17,
    "createdAt": "2026-04-01T18:37:34.754Z",
    "updatedAt": "2026-04-01T18:37:34.757Z",
    "category": "Food"
  }
]